4_Lab_Tail_Light_StateMachine/tailLight.vhd
-- 
-- Authors: Ian Flury, Joey Macauley
-- file: TLSM.vhd
-- comments: this code is a finite state machine that implements the tail-lights 
--           of a 1965 Ford Thunderbird on an Altera Cyclone family FPGA.
--

library ieee;
use ieee.std_logic_1164.all;
use ieee.std_logic_unsigned.all;
use ieee.numeric_std.all;
use work.all;


entity tailLight is 
    port (
        clock_slow  : in std_logic;
        RST         : in std_logic;
        switches    : in std_logic_vector(2 downto 0);
        lights      : out std_logic_vector(5 downto 0)
    );
end tailLight;


architecture rtl of tailLight is 
    type state_t is (off, hazard_zero, hazard_one, right_one, right_two, right_three, left_one, left_two, left_three);
    signal state, next_state : state_t;
    signal lights_state : std_logic_vector(5 downto 0); 
begin

    the_machine: process(switches, state, RST)
        variable l_count : unsigned(2 downto 0);
        variable r_count : unsigned(2 downto 0);
    begin

        if RST = '1' then
            lights_state <= (others => '0');
        else
            case state is
                when off =>
                    lights_state <= (others => '0');
                when hazard_zero =>
                    lights_state <= (others => '0');
                when hazard_one =>
                    lights_state <= (others => '1');
                when right_one =>
                    lights_state <= "000100";
                when right_two =>
                    lights_state <= "000110";
                when right_three =>
                    lights_state <= "000111";
                when left_one =>
                    lights_state <= "001000";
                when left_two =>
                    lights_state <= "011000";
                when left_three =>
                    lights_state <= "111000";
                when others =>
                    -- do nothing
            end case;
        end if;
    end process the_machine;

    lights <= lights_state;

    the_registers: process(clock_slow, RST)
    begin
        if RST = '1' then
            state <= off;
        elsif clock_slow'EVENT and clock_slow = '1' then
            if switches = "000" then
                state <= off;
            elsif switches(0) = '1' then
                -- hazard
                if state /= hazard_one then
                    state <= hazard_one;
                else
                    state <= hazard_zero;
                end if;
            elsif switches(2) = '1' then
                -- left signal
                if state = off then
                    state <= left_one;
                elsif state = left_one then
                    state <= left_two;
                elsif state = left_two then
                    state <= left_three;
                else
                    state <= off;
                end if;
            elsif switches(1) = '1' then
                -- right signals
                if state = off then
                    state <= right_one;
                elsif state = right_one then
                    state <= right_two;
                elsif state = right_two then
                    state <= right_three;
                else
                    state <= off;
                end if;
            end if;
        end if;
    end process the_registers;
end rtl;

4_Lab_Tail_Light_StateMachine/counter.vhd
library ieee;
use ieee.std_logic_1164.all;
use ieee.std_logic_unsigned.all;
use ieee.numeric_std.all;
use work.all;

entity counter is 
    port(
        clock       : in std_logic;
        RST         : in std_logic;
        clock_slow    : out std_logic
    );
end counter;

architecture rtl of counter is
    -- 25000000 / 24 is 24 Hz 
    --constant limit_c : integer := 1000000;
    constant limit_c : integer := 2;
begin

    counter_p: process(clock, RST)
        -- FIX: cannot set to zero right off the gate remove!
        variable count : unsigned(23 downto 0) := (others => '0');
        variable toggle : std_logic := '0';
    begin
        if RST = '1' then
            count := (others => '0');
        elsif clock'EVENT and clock = '1' then
            count := count + 1;
            if count > limit_c then
                -- if the counter's at the limit then reset it.
                count := (others => '0');
                if toggle = '0' then
                    toggle := '1';
                else 
                    toggle := '0';
                end if;
            end if;
        end if;
        clock_slow <= toggle;
        -- 1000000 is represented with 20 bits pick the high bit
    end process;

end rtl ; --counter

4_Lab_Tail_Light_StateMachine/toplevel.vhd
library ieee;
use ieee.std_logic_1164.all;
use ieee.std_logic_unsigned.all;
use ieee.numeric_std.all;
use work.all;


entity tail_light_top is
    port(
        clock_50M   : in std_logic;
        KEY3        : in std_logic;                         -- RST key
        SW          : in std_logic_vector(2 downto 0);
        lights      : out std_logic_vector(5 downto 0);
        clock_out   : out std_logic
    );
end tail_light_top;

architecture structural of tail_light_top is

component counter
    port(
        clock       : in std_logic;
        RST         : in std_logic;
        clock_slow  : out std_logic
    );
end component;

component tailLight
    port(
        clock_slow  : in std_logic;
        RST         : in std_logic;
        switches    : in std_logic_vector(2 downto 0);
        lights      : out std_logic_vector(5 downto 0)
    );
end component;

begin

    counter_1: counter port map(clock => clock_50M, RST => KEY3, clock_slow => clock_out);

    tailLight_1: tailLight port 
    map(
        clock_slow => clock_out,
        RST => KEY3,
        switches => SW,
        lights => lights
    );

end structural; -- tail_light_top

4_Lab_Tail_Light_StateMachine/TLSM_tb.vhd
-- 
-- Authors: Ian Flury, Joey Macauley
-- file: 
-- comments: 
--

library ieee;
use ieee.std_logic_1164.all;
use work.all;

entity tail_light_top_tb is
end tail_light_top_tb;

architecture tb of tail_light_top_tb is

    constant period_c   : time := 20 ns;
    signal clock_net    : std_logic;
    signal clock_slow   : std_logic;
    signal KEY3_net     : std_logic;
    signal SW_net       : std_logic_vector(2 downto 0);
    signal lights_net   : std_logic_vector(5 downto 0);

    component tail_light_top
        port(
            clock_50M   : in std_logic;
            KEY3        : in std_logic;                         -- RST key
            SW          : in std_logic_vector(2 downto 0);
            lights      : out std_logic_vector(5 downto 0);
            clock_out   : out std_logic
        );
    end component tail_light_top;

begin

    tail_light_top_instance: tail_light_top
    port map(
        clock_50M => clock_net,
        KEY3 => KEY3_net,
        SW => SW_net,
        lights => lights_net,
        clock_out => clock_slow
    );
    
    tb_clk: process
    begin
        clock_net <= '1';
        wait for period_c;
        clock_net <= '0';
        wait for period_c;
    end process;

    tb_p: process
    begin
        -- wait for 20 ns;
        -- SW_net <= (others => '0');
        -- KEY3_net <= '1';
        -- wait for 20 ns;
        -- KEY3_net <= '0';
        
        wait for 50 ns;
        SW_net <= "001";
        wait for 600 ns;

        SW_net <= "010";
        wait for 800 ns;

    assert false
    report "End of TestBench"
    severity failure;
    
    end process;
end tb; -- tail_light_top_tb

4_Lab_Tail_Light_StateMachine/tail_light_top.vcd
$date
	Sun Oct 15 11:25:19 2023
$end
$version
	ModelSim Version 2020.1
$end
$timescale
	1ps
$end

$scope module tail_light_top_tb $end

$scope module tail_light_top_instance $end
$var wire 1 ! clock_50M $end
$var wire 1 " KEY3 $end
$var wire 1 # SW [2] $end
$var wire 1 $ SW [1] $end
$var wire 1 % SW [0] $end
$var wire 1 & lights [5] $end
$var wire 1 ' lights [4] $end
$var wire 1 ( lights [3] $end
$var wire 1 ) lights [2] $end
$var wire 1 * lights [1] $end
$var wire 1 + lights [0] $end
$var wire 1 , clock_out $end
$upscope $end
$upscope $end
$enddefinitions $end
#0
$dumpvars
1!
x"
0,
x#
x$
x%
0&
0'
0(
0)
0*
0+
$end
#20000
0!
#40000
1!
#50000
1%
0$
0#
#60000
0!
#80000
1!
1,
1+
1*
1)
1(
1'
1&
#100000
0!
#120000
1!
#140000
0!
#160000
1!
#180000
0!
#200000
1!
0,
#220000
0!
#240000
1!
#260000
0!
#280000
1!
#300000
0!
#320000
1!
1,
0+
0*
0)
0(
0'
0&
#340000
0!
#360000
1!
#380000
0!
#400000
1!
#420000
0!
#440000
1!
0,
#460000
0!
#480000
1!
#500000
0!
#520000
1!
#540000
0!
#560000
1!
1,
1+
1*
1)
1(
1'
1&
#580000
0!
#600000
1!
#620000
0!
#640000
1!
#650000
0%
1$
#660000
0!
#680000
1!
0,
#700000
0!
#720000
1!
#740000
0!
#760000
1!
#780000
0!
#800000
1!
1,
0+
0*
0)
0(
0'
0&
#820000
0!
#840000
1!
#860000
0!
#880000
1!
#900000
0!
#920000
1!
0,
#940000
0!
#960000
1!
#980000
0!
#1000000
1!
#1020000
0!
#1040000
1!
1,
1)
#1060000
0!
#1080000
1!
#1100000
0!
#1120000
1!
#1140000
0!
#1160000
1!
0,
#1180000
0!
#1200000
1!
#1220000
0!
#1240000
1!
#1260000
0!
#1280000
1!
1,
1*
#1300000
0!
#1320000
1!
#1340000
0!
#1360000
1!
#1380000
0!
#1400000
1!
0,
#1420000
0!
#1440000
1!
#1460000
0!
#1480000
1!
#1500000
0!
1%
0$
#1520000
1!
1,
1+
1(
1'
1&
#1540000
0!
#1560000
1!
#1580000
0!
#1600000
1!
#1620000
0!
#1640000
1!
0,
#1660000
0!
#1680000
1!
#1700000
0!
#1720000
1!
#1740000
0!
#1760000
1!
1,
0+
0*
0)
0(
0'
0&
#1780000
0!
#1800000
1!
#1820000
0!
#1840000
1!
#1860000
0!
#1880000
1!
0,
#1900000
0!
#1920000
1!
#1940000
0!
#1960000
1!
#1980000
0!
#2000000
1!
1,
1+
1*
1)
1(
1'
1&
#2020000
0!
#2040000
1!
#2060000
0!
#2080000
1!
#2100000
0!
0%
1$
#2120000
1!
0,
#2140000
0!
#2160000
1!
#2180000
0!
#2200000
1!
#2220000
0!
#2240000
1!
1,
0+
0*
0)
0(
0'
0&
#2260000
0!
#2280000
1!
#2300000
0!
#2320000
1!
#2340000
0!
#2360000
1!
0,
#2380000
0!
#2400000
1!
#2420000
0!
#2440000
1!
#2460000
0!
#2480000
1!
1,
1)
#2500000
0!
#2520000
1!
#2540000
0!
#2560000
1!
#2580000
0!
#2600000
1!
0,
#2620000
0!
#2640000
1!
#2660000
0!
#2680000
1!
#2700000
0!
#2720000
1!
1,
1*
