Lab_2_Comparator/cmp.vhd
-- 
-- author:   Ian Flury
-- file:     cmp.vhd
-- comments: this code implements a 2-bit comparator
--

library ieee;
use ieee.std_logic_1164.all;
use work.all;



entity cmp is port(
	A: in std_logic_vector(1 downto 0);
	B: in std_logic_vector(1 downto 0);
	
	HEX0: out std_logic_vector(6 downto 0);
	HEX1: out std_logic_vector(6 downto 0);
	HEX2: out std_logic_vector(6 downto 0);
	HEX3: out std_logic_vector(6 downto 0);
	
	AGTB: out std_logic;
	AEQB: out std_logic;
	ALTB: out std_logic
	);

end cmp;

architecture rtl of cmp is
begin
 
  cmp_p: process(A,B)
  begin
  
	if (A = B) then
		AEQB <= '1';
		AGTB <= '0';
		ALTB <= '0';
		HEX0 <= "0000000";
		HEX1 <= "0011000";
		HEX2 <= "0000110";
		HEX3 <= "0001000";
	elsif (A < B) then
		AEQB <= '0';
		AGTB <= '0';
		ALTB <= '1';
		HEX0 <= "0000000";
		HEX1 <= "0000111";
		HEX2 <= "1000111";
		HEX3 <= "0001000";
	else
		AEQB <= '0';
		AGTB <= '1';
		ALTB <= '0';
		HEX0 <= "0000000";
		HEX1 <= "0000111";
		HEX2 <= "0000010";
		HEX3 <= "0001000";
	end if;
  
  end process cmp_p;
    
end rtl;

Lab_2_Comparator/cmp_tb.vhd
library ieee;
use ieee.std_logic_1164.all;
use work.all;

entity cmp_tb is
end cmp_tb;

architecture tb of cmp_tb is 
    signal A_net, B_net : std_logic_vector(1 downto 0);

    signal LED0_net : std_logic;
    signal LED1_net : std_logic;
    signal LED2_net : std_logic;

    signal HEX0_net : std_logic_vector(6 downto 0);
    signal HEX1_net : std_logic_vector(6 downto 0);
    signal HEX2_net : std_logic_vector(6 downto 0);
    signal HEX3_net : std_logic_vector(6 downto 0);

    component cmp
    port (
        A : in std_logic_vector(1 downto 0);
        B : in std_logic_vector(1 downto 0);

        AGTB : out std_logic;
        AEQB : out std_logic;
        ALTB : out std_logic;

        HEX0 : out std_logic_vector(6 downto 0);
        HEX1 : out std_logic_vector(6 downto 0);
        HEX2 : out std_logic_vector(6 downto 0);
        HEX3 : out std_logic_vector(6 downto 0)
    );
    end component cmp;

begin

    cmp_instance: cmp
    port map(
        A => A_net,
        B => B_net,
        HEX0 => HEX0_net,
        HEX1 => HEX1_net,
        HEX2 => HEX2_net,
        HEX3 => HEX3_net,
        AGTB => LED0_net,
        AEQB => LED1_net,
        ALTB => LED2_net
    );

    tb: process
    begin
        A_net <= "00";
        B_net <= "00";
        wait for 100 ns;

        A_net <= "01";
        B_net <= "00";
        wait for 100 ns;

        A_net <= "00";
        B_net <= "01";
        wait for 100 ns;

        A_net <= "01";
        B_net <= "01";
        wait for 100 ns;

        A_net <= "10";
        B_net <= "00";
        wait for 100 ns;

        A_net <= "00";
        B_net <= "10";
        wait for 100 ns;

        A_net <= "10";
        B_net <= "10";
        wait for 100 ns;

        A_net <= "11";
        B_net <= "00";
        wait for 100 ns;

        A_net <= "00";
        B_net <= "11";
        wait for 100 ns;

        A_net <= "11";
        B_net <= "01";
        wait for 100 ns;

        A_net <= "01";
        B_net <= "11";
        wait for 100 ns;

        A_net <= "11";
        B_net <= "11";
        wait for 100 ns;

        A_net <= "10";
        B_net <= "01";
        wait for 100 ns;

        A_net <= "01";
        B_net <= "10";
        wait for 100 ns;

        A_net <= "10";
        B_net <= "11";
        wait for 100 ns;

        A_net <= "11";
        B_net <= "10";
        wait for 100 ns;

        assert false
        report "End of TestBench"
        severity failure;

    end process tb;
end tb;

Lab_2_Comparator/cmp.vcd
$date
	Tue Sep 19 10:13:06 2023
$end
$version
	ModelSim Version 2020.1
$end
$timescale
	1ps
$end

$scope module cmp_tb $end

$scope module cmp_instance $end
$var wire 1 ! A [1] $end
$var wire 1 " A [0] $end
$var wire 1 # B [1] $end
$var wire 1 $ B [0] $end
$var wire 1 % HEX0 [6] $end
$var wire 1 & HEX0 [5] $end
$var wire 1 ' HEX0 [4] $end
$var wire 1 ( HEX0 [3] $end
$var wire 1 ) HEX0 [2] $end
$var wire 1 * HEX0 [1] $end
$var wire 1 + HEX0 [0] $end
$var wire 1 , HEX1 [6] $end
$var wire 1 - HEX1 [5] $end
$var wire 1 . HEX1 [4] $end
$var wire 1 / HEX1 [3] $end
$var wire 1 0 HEX1 [2] $end
$var wire 1 1 HEX1 [1] $end
$var wire 1 2 HEX1 [0] $end
$var wire 1 3 HEX2 [6] $end
$var wire 1 4 HEX2 [5] $end
$var wire 1 5 HEX2 [4] $end
$var wire 1 6 HEX2 [3] $end
$var wire 1 7 HEX2 [2] $end
$var wire 1 8 HEX2 [1] $end
$var wire 1 9 HEX2 [0] $end
$var wire 1 : HEX3 [6] $end
$var wire 1 ; HEX3 [5] $end
$var wire 1 < HEX3 [4] $end
$var wire 1 = HEX3 [3] $end
$var wire 1 > HEX3 [2] $end
$var wire 1 ? HEX3 [1] $end
$var wire 1 @ HEX3 [0] $end
$var wire 1 A AGTB $end
$var wire 1 B AEQB $end
$var wire 1 C ALTB $end
$upscope $end
$upscope $end
$enddefinitions $end
#0
$dumpvars
0A
1B
0C
0!
0"
0#
0$
0%
0&
0'
0(
0)
0*
0+
0,
0-
1.
1/
00
01
02
03
04
05
06
17
18
09
0:
0;
0<
1=
0>
0?
0@
$end
#100000
1"
07
12
11
10
0/
0.
1A
0B
#200000
1$
0"
19
17
13
1C
0A
#300000
1"
09
03
02
01
00
1/
1.
0C
1B
#400000
0$
0"
1!
07
12
11
10
0/
0.
1A
0B
#500000
1#
0!
19
17
13
1C
0A
#600000
1!
09
03
02
01
00
1/
1.
0C
1B
#700000
0#
1"
07
12
11
10
0/
0.
1A
0B
#800000
1$
1#
0"
0!
19
17
13
1C
0A
#900000
0#
1"
1!
09
07
03
0C
1A
#1000000
1#
0!
19
17
13
1C
0A
#1100000
1!
09
03
02
01
00
1/
1.
0C
1B
#1200000
0#
0"
07
12
11
10
0/
0.
1A
0B
#1300000
0$
1#
1"
0!
19
17
13
1C
0A
#1400000
1$
0"
1!
#1500000
0$
1"
09
07
03
0C
1A
