3_Lab_SwitchDebounce/swdbnc.vhd
-- 
-- Authors: Ian Flury, Joey Macauley
-- file: swdbnc.vhd
-- comments: this code implements a hardware button/switch swdbnc.
--           CLK = 50MHz -> period of 20 ns
--

library ieee;
use ieee.std_logic_1164.all;
use ieee.std_logic_unsigned.all;
use ieee.numeric_std.all;
use work.all;

-- 2,500,000 clock cycles is 50ms
-- Note: you cannot initialize anything in hardware.
-- instead you should add a RST to the counter to set
-- it to zero and start counting from there.



entity swdbnc is port(
    CLK_50M         : in std_logic;
    KEY0  			: in std_logic;
    KEY3			: in std_logic;
    LEDG0 			: out std_logic
    );
end swdbnc;
     
architecture rtl of swdbnc is
    
     constant LIMIT_c : integer := 10;
     signal ENAB1		 : std_logic;
     signal ENAB2 		 : std_logic;
     signal RST			 : std_logic;
     signal LED_FLAG     : std_logic;
     signal led_flag_off : std_logic;
     signal rst_state	 : std_logic;
     
     signal prev_state : std_logic;
     signal cur_state : std_logic;
     signal led_state : std_logic;

begin

    pressed_p: process(CLK_50M)
    begin
        if CLK_50M'EVENT and CLK_50M = '1' then
            if (KEY0 <= '0') and (prev_state = '1') then
                ENAB1 <= '1';
                prev_state <= KEY0;
                else
                prev_state <= KEY0;
            end if;
        else
        end if;
    end process;


    timer1: process(CLK_50M)
        variable count1 : unsigned(21 downto 0);
    begin
        if CLK_50M'EVENT and CLK_50M = '1' then
            if RST = '1' then
                count1 := (others => '0');
            elsif rst_state = '1' then
                count1 := (others => '0');
            elsif ENAB1 = '1' then
                count1 := count1 + 1;
                if count1 > LIMIT_c then
                    ENAB2 <= '1';
                else
                    
                end if;
            else
            end if;
        else
        end if;
    end process;
    
    
    timer2_p: process(CLK_50M)
        variable count2 : unsigned(21 downto 0);
    begin
        if CLK_50M'EVENT and CLK_50M = '1' then
            if RST = '1' then
                count2 := (others => '0');
            elsif led_flag_off = '1' then
                LED_FLAG <= '0';
            elsif rst_state = '1' then
                count2 := (others => '0');
                --LED_FLAG <= '0';
            elsif ENAB2 = '1' then
                count2 := count2 + 1;
                if count2 > LIMIT_c then
                    LED_FLAG <= '1';
                    led_flag_off <= '1';
                else
                    
                end if;
            else
            end if;
        else
        end if;
    end process;

    led_p: process(CLK_50M)
    begin
        if CLK_50M'EVENT and CLK_50M = '1' then
            if RST = '1' then
                led_state <= '0';
                LEDG0 <= '0';
            elsif LED_FLAG = '1' then
                if KEY0 = '1' then
                    led_state <= not led_state;
                    rst_state <= '1';
                else
                end if;
            else
            end if;
        else
        end if;
        LEDG0 <= led_state;
    end process;


    reset_p: process(CLK_50M)
    begin
        -- need to set previous state back to 1 to make the first process to work
        if CLK_50M'EVENT and CLK_50M = '1' then
            if KEY3 = '0' then 
                RST <= '1';
            else
                RST <= '0';
            end if;
        else
        end if;
    end process;

end rtl;

3_Lab_SwitchDebounce/swdbnc_tb.vhd
library ieee;
use ieee.std_logic_1164.all;
use work.all;

entity swdbnc_tb is
end swdbnc_tb;

architecture tb of swdbnc_tb is 
    constant period_c : time := 10 ns;
    
    signal CLK_50M_net  : std_logic;
    signal KEY0_net     : std_logic;
    signal KEY3_net     : std_logic;
    signal LEDG0_net    : std_logic;

    component swdbnc
    port (
        CLK_50M     : in std_logic;	 
        KEY0        : in std_logic;
        KEY3        : in std_logic;    
        LEDG0       : out std_logic
    ); 
    end component swdbnc;

begin

    swdbnc_instance: swdbnc
    port map(
        CLK_50M => CLK_50M_net,
        KEY0    => KEY0_net,
        KEY3    => KEY3_net,
        LEDG0   => LEDG0_net
    );

    tb_clk: process
        begin
            CLK_50M_net <= '1';
            wait for period_c / 2;
            CLK_50M_net <= '0';
            wait for period_c / 2;
    end process tb_clk;

    tb: process
        begin
            KEY3_net <= '0';
            wait for 50 ns;
            KEY3_net <= '1';
            wait for 25 ns;
            
            KEY0_net <= '1';
            wait for 50 ns;
            KEY0_net <= '0';
            wait for 50 ns;
            KEY0_net <= '1';



            wait for 350 ns;
        assert false
        report "End of TestBench"
        severity failure;

    end process tb;
end tb;

3_Lab_SwitchDebounce/swdbnc.vcd
$date
	Fri Sep 29 10:54:02 2023
$end
$version
	ModelSim Version 2020.1
$end
$timescale
	1ps
$end

$scope module swdbnc_tb $end

$scope module swdbnc_instance $end
$var wire 1 ! CLK_50M $end
$var wire 1 " KEY0 $end
$var wire 1 # KEY3 $end
$var wire 1 $ LEDG0 $end
$var wire 1 % ENAB1 $end
$var wire 1 & ENAB2 $end
$var wire 1 ' RST $end
$var wire 1 ( LED_FLAG $end
$var wire 1 ) led_flag_off $end
$var wire 1 * rst_state $end
$var wire 1 + prev_state $end
$var wire 1 , cur_state $end
$var wire 1 - led_state $end
$upscope $end
$upscope $end
$enddefinitions $end
#0
$dumpvars
1!
x"
0#
x$
x%
x&
1'
x(
x)
x*
x+
x,
x-
$end
#5000
0!
#10000
1!
0-
#15000
0!
0$
#20000
1!
#25000
0!
#30000
1!
#35000
0!
#40000
1!
#45000
0!
#50000
1!
1#
0'
#55000
0!
#60000
1!
#65000
0!
#70000
1!
#75000
0!
1"
#80000
1!
1+
#85000
0!
#90000
1!
#95000
0!
#100000
1!
#105000
0!
#110000
1!
#115000
0!
#120000
1!
#125000
0!
0"
#130000
1!
0+
1%
#135000
0!
#140000
1!
#145000
0!
#150000
1!
#155000
0!
#160000
1!
#165000
0!
#170000
1!
#175000
0!
1"
#180000
1!
1+
#185000
0!
#190000
1!
#195000
0!
#200000
1!
#205000
0!
#210000
1!
#215000
0!
#220000
1!
#225000
0!
#230000
1!
#235000
0!
#240000
1!
1&
#245000
0!
#250000
1!
#255000
0!
#260000
1!
#265000
0!
#270000
1!
#275000
0!
#280000
1!
#285000
0!
#290000
1!
#295000
0!
#300000
1!
#305000
0!
#310000
1!
#315000
0!
#320000
1!
#325000
0!
#330000
1!
#335000
0!
#340000
1!
#345000
0!
#350000
1!
1)
1(
#355000
0!
#360000
1!
1*
1-
0(
#365000
0!
1$
