3_Lab_SwitchDebounce/swdbnc.vhd
-- 
-- Authors: Ian Flury, Joey Macauley
-- file: swdbnc.vhd
-- comments: this code implements a hardware button/switch swdbnc.
--           CLK = 50MHz -> period of 20 ns
--

library ieee;
use ieee.std_logic_1164.all;
use ieee.std_logic_unsigned.all;
use ieee.numeric_std.all;
use work.all;

-- 2,500,000 clock cycles is 50ms
-- Note: you cannot initialize anything in hardware.
-- instead you should add a RST to the counter to set
-- it to zero and start counting from there.



entity swdbnc is port(
    CLK_50M         : in std_logic;
    KEY0  			: in std_logic;
    KEY3			: in std_logic;
    LEDG0 			: out std_logic
    );
end swdbnc;
     
architecture rtl of swdbnc is
    
    -- set LIMIT_c to 10 for simulation
    -- should be 2500000 for synthesis
     constant LIMIT_c : integer := 10;
     signal ENAB1		 : std_logic;
     signal ENAB2 		 : std_logic;
     signal RST			 : std_logic;
     signal LED_FLAG     : std_logic;
     signal led_flag_off : std_logic;
     signal rst_state	 : std_logic;
     
     signal prev_state : std_logic;
     signal led_state : std_logic;

begin

    pressed_p: process(CLK_50M)
    begin
        if CLK_50M'EVENT and CLK_50M = '1' then
            if rst_state = '1' then
                ENAB1 <= '0';
                prev_state <= KEY0;
            elsif (KEY0 <= '0') and (prev_state = '1') then
                ENAB1 <= '1';
                prev_state <= KEY0;
            else
                prev_state <= KEY0;
            end if;
        end if;
    end process;


    timer1: process(CLK_50M)
        variable count1 : unsigned(21 downto 0);
    begin
        if CLK_50M'EVENT and CLK_50M = '1' then
            if RST = '1' then
                count1 := (others => '0');
                ENAB2 <= '0';
            elsif rst_state = '1' then
                count1 := (others => '0');
                ENAB2 <= '0';
            elsif ENAB1 = '1' then
                count1 := count1 + 1;
                if count1 > LIMIT_c then
                    ENAB2 <= '1';
                end if;
            end if;
        end if;
    end process;
    
    
    timer2_p: process(CLK_50M)
        variable count2 : unsigned(21 downto 0);
    begin
        if CLK_50M'EVENT and CLK_50M = '1' then
            if RST = '1' then
                count2 := (others => '0');
                LED_FLAG <= '0';
            elsif led_flag_off = '1' then
                LED_FLAG <= '0';
                led_flag_off <= '0'; 
            elsif rst_state = '1' then
                count2 := (others => '0');
                led_flag <= '0';
            elsif ENAB2 = '1' then
                count2 := count2 + 1;
                if count2 > LIMIT_c then
                    LED_FLAG <= '1';
                    led_flag_off <= '1';
                else
                    
                end if;
            end if;
        end if;
    end process;

    led_p: process(CLK_50M)
    begin
        if CLK_50M'EVENT and CLK_50M = '1' then
            if RST = '1' then
                led_state <= '0';
                rst_state <= '1';
            elsif rst_state = '1' then
                rst_state <= '0';
            elsif LED_FLAG = '1' then
                if KEY0 = '1' then
                    led_state <= not led_state;
                    rst_state <= '1';
                end if;
            end if;
        end if;
        end process;
    LEDG0 <= led_state;


    reset_p: process(CLK_50M)
    begin
        -- need to set previous state back to 1 to make the first process to work
        if CLK_50M'EVENT and CLK_50M = '1' then
            if KEY3 = '0' then 
                RST <= '1';
            else
                RST <= '0';
            end if;
        end if;
    end process;

end rtl;

3_Lab_SwitchDebounce/swdbnc_tb.vhd
-- 
-- Authors: Ian Flury, Joey Macauley
-- file: swdbnc_tb.vhd
-- comments: This code implements a basic TestBench for the 
--           switch debouncer circuit defined in swdbnc.vhd
--

library ieee;
use ieee.std_logic_1164.all;
use work.all;

entity swdbnc_tb is
end swdbnc_tb;

architecture tb of swdbnc_tb is 
    constant period_c : time := 10 ns;
    
    signal CLK_50M_net  : std_logic;
    signal KEY0_net     : std_logic;
    signal KEY3_net     : std_logic;
    signal LEDG0_net    : std_logic;

    component swdbnc
    port (
        CLK_50M     : in std_logic;	 
        KEY0        : in std_logic;
        KEY3        : in std_logic;    
        LEDG0       : out std_logic
    ); 
    end component swdbnc;

begin

    swdbnc_instance: swdbnc
    port map(
        CLK_50M => CLK_50M_net,
        KEY0    => KEY0_net,
        KEY3    => KEY3_net,
        LEDG0   => LEDG0_net
    );

    tb_clk: process
        begin
            CLK_50M_net <= '1';
            wait for period_c / 2;
            CLK_50M_net <= '0';
            wait for period_c / 2;
    end process tb_clk;

    tb: process
        begin
            -- setup signals
            KEY0_net <= '1';
            
            -- do a reset
            KEY3_net <= '0';
            wait for 50 ns;
            KEY3_net <= '1';
            wait for 25 ns;
            
            -- first button press
            KEY0_net <= '1';
            wait for 50 ns;
            KEY0_net <= '0';
            wait for 50 ns;
            KEY0_net <= '1';

            wait for 350 ns;

            -- second button press
            KEY0_net <= '0';
            wait for 50 ns;
            KEY0_net <= '1';

            wait for 350 ns;

        assert false
        report "End of TestBench"
        severity failure;

    end process tb;
end tb;

3_Lab_SwitchDebounce/swdbnc.vcd
$date
	Tue Oct 03 12:07:29 2023
$end
$version
	ModelSim Version 2020.1
$end
$timescale
	1ps
$end

$scope module swdbnc_tb $end

$scope module swdbnc_instance $end
$var wire 1 ! CLK_50M $end
$var wire 1 " KEY0 $end
$var wire 1 # KEY3 $end
$var wire 1 $ LEDG0 $end
$var wire 1 % ENAB1 $end
$var wire 1 & ENAB2 $end
$var wire 1 ' RST $end
$var wire 1 ( LED_FLAG $end
$var wire 1 ) led_flag_off $end
$var wire 1 * rst_state $end
$var wire 1 + prev_state $end
$var wire 1 , led_state $end
$upscope $end
$upscope $end
$enddefinitions $end
#0
$dumpvars
1!
1"
0#
x$
x%
x&
1'
x(
x)
x*
1+
x,
$end
#5000
0!
#10000
1!
1*
0,
0(
0&
0$
#15000
0!
#20000
1!
0%
#25000
0!
#30000
1!
#35000
0!
#40000
1!
#45000
0!
#50000
1!
1#
0'
#55000
0!
#60000
1!
0*
#65000
0!
#70000
1!
#75000
0!
#80000
1!
#85000
0!
#90000
1!
#95000
0!
#100000
1!
#105000
0!
#110000
1!
#115000
0!
#120000
1!
#125000
0!
0"
#130000
1!
0+
1%
#135000
0!
#140000
1!
#145000
0!
#150000
1!
#155000
0!
#160000
1!
#165000
0!
#170000
1!
#175000
0!
1"
#180000
1!
1+
#185000
0!
#190000
1!
#195000
0!
#200000
1!
#205000
0!
#210000
1!
#215000
0!
#220000
1!
#225000
0!
#230000
1!
#235000
0!
#240000
1!
1&
#245000
0!
#250000
1!
#255000
0!
#260000
1!
#265000
0!
#270000
1!
#275000
0!
#280000
1!
#285000
0!
#290000
1!
#295000
0!
#300000
1!
#305000
0!
#310000
1!
#315000
0!
#320000
1!
#325000
0!
#330000
1!
#335000
0!
#340000
1!
#345000
0!
#350000
1!
1)
1(
#355000
0!
#360000
1!
1*
1,
0)
0(
1$
#365000
0!
#370000
1!
0*
0&
0%
#375000
0!
#380000
1!
#385000
0!
#390000
1!
#395000
0!
#400000
1!
#405000
0!
#410000
1!
#415000
0!
#420000
1!
#425000
0!
#430000
1!
#435000
0!
#440000
1!
#445000
0!
#450000
1!
#455000
0!
#460000
1!
#465000
0!
#470000
1!
#475000
0!
#480000
1!
#485000
0!
#490000
1!
#495000
0!
#500000
1!
#505000
0!
#510000
1!
#515000
0!
#520000
1!
#525000
0!
0"
#530000
1!
0+
1%
#535000
0!
#540000
1!
#545000
0!
#550000
1!
#555000
0!
#560000
1!
#565000
0!
#570000
1!
#575000
0!
1"
#580000
1!
1+
#585000
0!
#590000
1!
#595000
0!
#600000
1!
#605000
0!
#610000
1!
#615000
0!
#620000
1!
#625000
0!
#630000
1!
#635000
0!
#640000
1!
1&
#645000
0!
#650000
1!
#655000
0!
#660000
1!
#665000
0!
#670000
1!
#675000
0!
#680000
1!
#685000
0!
#690000
1!
#695000
0!
#700000
1!
#705000
0!
#710000
1!
#715000
0!
#720000
1!
#725000
0!
#730000
1!
#735000
0!
#740000
1!
#745000
0!
#750000
1!
1)
1(
#755000
0!
#760000
1!
1*
0,
0)
0(
0$
#765000
0!
#770000
1!
0*
0&
0%
